lzypac/__init__.py
lzypac/tests/test.py
lzypac-0.0.1.dist-info/METADATA
lzypac-0.0.1.dist-info/WHEEL
lzypac-0.0.1.dist-info/top_level.txt
lzypac-0.0.1.dist-info/RECORD
